{"stat.pickup.minecraft.log":2,"stat.flyOneCm":7183,"stat.walkOneCm":4938,"stat.jump":35,"stat.mineBlock.minecraft.leaves":3,"stat.useItem.minecraft.sapling":1,"stat.playOneMinute":4224,"stat.fallOneCm":1438,"stat.horseOneCm":2871,"stat.leaveGame":1,"stat.sneakTime":11,"stat.crouchOneCm":53,"stat.timeSinceDeath":4224,"stat.pickup.minecraft.sapling":2,"stat.sprintOneCm":10685,"stat.useItem.minecraft.stone_slab2":1,"stat.mineBlock.minecraft.log":2,"stat.mineBlock.actuallyadditions.block_giant_chest":1,"stat.pickup.actuallyadditions.block_giant_chest":1,"stat.talkedToVillager":1}